dl4phylo/__init__.py
dl4phylo/attentions.py
dl4phylo/data.py
dl4phylo/metrics.py
dl4phylo/model.py
dl4phylo/training.py
dl4phylo/utils.py
dl4phylo/scripts/__init__.py
dl4phylo/scripts/alignment_trimmer.py
dl4phylo/scripts/evaluate.py
dl4phylo/scripts/make_tensors.py
dl4phylo/scripts/predict.py
dl4phylo/scripts/predict_true_trees.py
dl4phylo/scripts/simulate_dataset_SeqGen.py
dl4phylo/scripts/simulate_dataset_SimBac.py
dl4phylo/scripts/simulate_typing_data.py
dl4phylo/scripts/train_tensorboard.py
dl4phylo/scripts/train_wandb.py
DL4Phylo-0.0.3.dist-info/METADATA
DL4Phylo-0.0.3.dist-info/WHEEL
DL4Phylo-0.0.3.dist-info/entry_points.txt
DL4Phylo-0.0.3.dist-info/top_level.txt
DL4Phylo-0.0.3.dist-info/RECORD
