Metadata-Version: 2.1
Name: DL4Phylo
Version: 0.0.3
Summary: Deep Learning techniques applied to Phylogenetic Analysis
Home-page: https://github.com/phyloLearn/DL4Phylo
Author: Miguel Raposo, Gonçalo Silva
License: CeCILL
Requires-Python: >=3.9, <3.13
Requires-Dist: torch >=1.13.1
Requires-Dist: scipy >=1.7.3
Requires-Dist: numpy <2.0.0,>=1.21.2
Requires-Dist: ete3 >=3.1.2
Requires-Dist: biopython >=1.79
Requires-Dist: dendropy >=4.5.2
Requires-Dist: scikit-bio >=0.5.6
Requires-Dist: scikit-learn >=1.4.2
Requires-Dist: tqdm >=4.65.0
Requires-Dist: wandb >=0.17.3
Provides-Extra: dev
Requires-Dist: twine !=5.1.0,>=4.0.2 ; extra == 'dev'
